{
  "topic": "positivity",
  "generatedAt": "2026-04-05T01:48:23.813Z",
  "videos": [
    {
      "id": "yt:video:TU1-WrlBxHM",
      "title": "What is Anxious Attachment",
      "videoId": "TU1-WrlBxHM",
      "channel": "Therapy in a Nutshell",
      "publishedAt": "2026-04-04T10:00:41.000Z",
      "thumbnail": "https://i.ytimg.com/vi/TU1-WrlBxHM/hqdefault.jpg",
      "tags": []
    },
    {
      "id": "yt:video:NGr1f5io0Lo",
      "title": "CPTSD and Relational Reactivity",
      "videoId": "NGr1f5io0Lo",
      "channel": "Therapy in a Nutshell",
      "publishedAt": "2026-04-03T16:00:38.000Z",
      "thumbnail": "https://i.ytimg.com/vi/NGr1f5io0Lo/hqdefault.jpg",
      "tags": []
    },
    {
      "id": "yt:video:H-LGg14XiXc",
      "title": "3 Essential Strategies for Managing Burnout for Modern Knowledge Workers",
      "videoId": "H-LGg14XiXc",
      "channel": "Therapy in a Nutshell",
      "publishedAt": "2026-04-02T13:00:24.000Z",
      "thumbnail": "https://i.ytimg.com/vi/H-LGg14XiXc/hqdefault.jpg",
      "tags": []
    },
    {
      "id": "yt:video:gpI8fA2ZTpI",
      "title": "Medical Trauma is Re-Traumatizing",
      "videoId": "gpI8fA2ZTpI",
      "channel": "Therapy in a Nutshell",
      "publishedAt": "2026-04-01T16:00:49.000Z",
      "thumbnail": "https://i.ytimg.com/vi/gpI8fA2ZTpI/hqdefault.jpg",
      "tags": []
    },
    {
      "id": "yt:video:oni4xBdx4rk",
      "title": "You Can’t Just Try Harder to Be Less Reactive",
      "videoId": "oni4xBdx4rk",
      "channel": "Therapy in a Nutshell",
      "publishedAt": "2026-03-31T16:01:01.000Z",
      "thumbnail": "https://i.ytimg.com/vi/oni4xBdx4rk/hqdefault.jpg",
      "tags": []
    },
    {
      "id": "yt:video:fsXF0WinEa0",
      "title": "How to Get Out of Freeze",
      "videoId": "fsXF0WinEa0",
      "channel": "Therapy in a Nutshell",
      "publishedAt": "2026-03-30T16:00:59.000Z",
      "thumbnail": "https://i.ytimg.com/vi/fsXF0WinEa0/hqdefault.jpg",
      "tags": []
    },
    {
      "id": "yt:video:1iAMtXYr9DA",
      "title": "Dealing with Physical Symptoms of Anxiety",
      "videoId": "1iAMtXYr9DA",
      "channel": "Therapy in a Nutshell",
      "publishedAt": "2026-03-29T16:00:03.000Z",
      "thumbnail": "https://i.ytimg.com/vi/1iAMtXYr9DA/hqdefault.jpg",
      "tags": []
    },
    {
      "id": "yt:video:UKaFzji9uf8",
      "title": "You Don’t Have to Believe Your Thoughts",
      "videoId": "UKaFzji9uf8",
      "channel": "Therapy in a Nutshell",
      "publishedAt": "2026-03-28T16:00:26.000Z",
      "thumbnail": "https://i.ytimg.com/vi/UKaFzji9uf8/hqdefault.jpg",
      "tags": []
    },
    {
      "id": "yt:video:T7m_oKFEQyI",
      "title": "The Secret Fuel of Social Anxiety",
      "videoId": "T7m_oKFEQyI",
      "channel": "Therapy in a Nutshell",
      "publishedAt": "2026-03-28T10:01:13.000Z",
      "thumbnail": "https://i.ytimg.com/vi/T7m_oKFEQyI/hqdefault.jpg",
      "tags": []
    },
    {
      "id": "yt:video:vrvAC2zzSxk",
      "title": "You're Not going to Make Me Do Exposure Therapy, are You?",
      "videoId": "vrvAC2zzSxk",
      "channel": "Therapy in a Nutshell",
      "publishedAt": "2026-03-27T16:01:13.000Z",
      "thumbnail": "https://i.ytimg.com/vi/vrvAC2zzSxk/hqdefault.jpg",
      "tags": []
    },
    {
      "id": "yt:video:B8XW3UGXeOs",
      "title": "Social Anxiety Skills That Actually Help w/  Dr.  Deborah Dobson",
      "videoId": "B8XW3UGXeOs",
      "channel": "Therapy in a Nutshell",
      "publishedAt": "2026-03-26T12:12:35.000Z",
      "thumbnail": "https://i.ytimg.com/vi/B8XW3UGXeOs/hqdefault.jpg",
      "tags": []
    },
    {
      "id": "yt:video:Q_QZG612KkA",
      "title": "How Neglect Changes the Brain",
      "videoId": "Q_QZG612KkA",
      "channel": "Therapy in a Nutshell",
      "publishedAt": "2026-03-25T16:00:39.000Z",
      "thumbnail": "https://i.ytimg.com/vi/Q_QZG612KkA/hqdefault.jpg",
      "tags": []
    },
    {
      "id": "yt:video:QbwiVvvRvXE",
      "title": "Getting Stuck in a Trauma Cycle",
      "videoId": "QbwiVvvRvXE",
      "channel": "Therapy in a Nutshell",
      "publishedAt": "2026-03-24T16:00:45.000Z",
      "thumbnail": "https://i.ytimg.com/vi/QbwiVvvRvXE/hqdefault.jpg",
      "tags": []
    },
    {
      "id": "yt:video:m-JN4jydMVQ",
      "title": "How Trauma Makes us Reactive",
      "videoId": "m-JN4jydMVQ",
      "channel": "Therapy in a Nutshell",
      "publishedAt": "2026-03-23T16:01:13.000Z",
      "thumbnail": "https://i.ytimg.com/vi/m-JN4jydMVQ/hqdefault.jpg",
      "tags": []
    },
    {
      "id": "yt:video:ROHuTvoZIjU",
      "title": "The Fawn State",
      "videoId": "ROHuTvoZIjU",
      "channel": "Therapy in a Nutshell",
      "publishedAt": "2026-03-22T16:00:39.000Z",
      "thumbnail": "https://i.ytimg.com/vi/ROHuTvoZIjU/hqdefault.jpg",
      "tags": []
    }
  ],
  "articles": [
    {
      "id": "link:https://positivepsychology.com/identity-at-work/?utm_source=rss&utm_medium=rss&utm_campaign=identity-at-work",
      "title": "Your Identity at Work: Why It Matters & How It Changes",
      "url": "https://positivepsychology.com/identity-at-work/?utm_source=rss&utm_medium=rss&utm_campaign=identity-at-work",
      "source": "PositivePsychology.com",
      "publishedAt": "2026-04-02T09:00:24.000Z",
      "tags": []
    },
    {
      "id": "link:https://positivepsychology.com/recognition-at-work/?utm_source=rss&utm_medium=rss&utm_campaign=recognition-at-work",
      "title": "Recognition at Work & How to Ask for Feedback",
      "url": "https://positivepsychology.com/recognition-at-work/?utm_source=rss&utm_medium=rss&utm_campaign=recognition-at-work",
      "source": "PositivePsychology.com",
      "publishedAt": "2026-04-01T09:00:43.000Z",
      "tags": []
    },
    {
      "id": "link:https://positivepsychology.com/resilience-group-curriculum/?utm_source=rss&utm_medium=rss&utm_campaign=resilience-group-curriculum",
      "title": "6-Week Resilience Group Curriculum for Practitioners",
      "url": "https://positivepsychology.com/resilience-group-curriculum/?utm_source=rss&utm_medium=rss&utm_campaign=resilience-group-curriculum",
      "source": "PositivePsychology.com",
      "publishedAt": "2026-03-30T09:00:10.000Z",
      "tags": []
    },
    {
      "id": "link:https://positivepsychology.com/impostor-syndrome-and-self-esteem/?utm_source=rss&utm_medium=rss&utm_campaign=impostor-syndrome-and-self-esteem",
      "title": "Impostor Syndrome and Self-Esteem: How They Relate",
      "url": "https://positivepsychology.com/impostor-syndrome-and-self-esteem/?utm_source=rss&utm_medium=rss&utm_campaign=impostor-syndrome-and-self-esteem",
      "source": "PositivePsychology.com",
      "publishedAt": "2026-03-26T10:00:06.000Z",
      "tags": []
    },
    {
      "id": "link:https://positivepsychology.com/self-esteem-resources/?utm_source=rss&utm_medium=rss&utm_campaign=self-esteem-resources",
      "title": "Self-Esteem Resources Gateway: Choose the Right Next Step",
      "url": "https://positivepsychology.com/self-esteem-resources/?utm_source=rss&utm_medium=rss&utm_campaign=self-esteem-resources",
      "source": "PositivePsychology.com",
      "publishedAt": "2026-03-25T10:00:21.000Z",
      "tags": []
    },
    {
      "id": "link:https://positivepsychology.com/coping-cards/?utm_source=rss&utm_medium=rss&utm_campaign=coping-cards",
      "title": "Coping Cards: Tiny Tools for Big Relief",
      "url": "https://positivepsychology.com/coping-cards/?utm_source=rss&utm_medium=rss&utm_campaign=coping-cards",
      "source": "PositivePsychology.com",
      "publishedAt": "2026-03-24T10:00:00.000Z",
      "tags": []
    },
    {
      "id": "link:https://positivepsychology.com/healthy-vs-fragile-self-esteem/?utm_source=rss&utm_medium=rss&utm_campaign=healthy-vs-fragile-self-esteem",
      "title": "Healthy vs. Fragile Self-Esteem: Why Distinction Matters",
      "url": "https://positivepsychology.com/healthy-vs-fragile-self-esteem/?utm_source=rss&utm_medium=rss&utm_campaign=healthy-vs-fragile-self-esteem",
      "source": "PositivePsychology.com",
      "publishedAt": "2026-03-23T10:00:06.000Z",
      "tags": []
    },
    {
      "id": "link:https://positivepsychology.com/mindfulness-for-sleep/?utm_source=rss&utm_medium=rss&utm_campaign=mindfulness-for-sleep",
      "title": "Mindfulness for Sleep: When Your Mind Won’t Slow Down",
      "url": "https://positivepsychology.com/mindfulness-for-sleep/?utm_source=rss&utm_medium=rss&utm_campaign=mindfulness-for-sleep",
      "source": "PositivePsychology.com",
      "publishedAt": "2026-03-19T10:00:21.000Z",
      "tags": []
    },
    {
      "id": "link:https://positivepsychology.com/digital-distraction/?utm_source=rss&utm_medium=rss&utm_campaign=digital-distraction",
      "title": "Avoid Digital Distraction With These Mindfulness Practices",
      "url": "https://positivepsychology.com/digital-distraction/?utm_source=rss&utm_medium=rss&utm_campaign=digital-distraction",
      "source": "PositivePsychology.com",
      "publishedAt": "2026-03-18T10:00:05.000Z",
      "tags": []
    },
    {
      "id": "link:https://positivepsychology.com/practicelab-worksheets-vol2/?utm_source=rss&utm_medium=rss&utm_campaign=practicelab-worksheets-vol2",
      "title": "How PracticeLab Volume 2 Equips You for Client Challenges",
      "url": "https://positivepsychology.com/practicelab-worksheets-vol2/?utm_source=rss&utm_medium=rss&utm_campaign=practicelab-worksheets-vol2",
      "source": "PositivePsychology.com",
      "publishedAt": "2026-03-17T10:00:20.000Z",
      "tags": []
    }
  ]
}